{
  "timelines": {
    "default": {
      "frames": [
        {
          "duration": 200,
          "offset": {
            "x": 46,
            "y": 197
          },
          "quad": {
            "x": 1,
            "y": 1,
            "w": 15,
            "h": 33
          }
        },
        {
          "duration": 200,
          "offset": {
            "x": 46,
            "y": 197
          },
          "quad": {
            "x": 18,
            "y": 1,
            "w": 15,
            "h": 33
          }
        },
        {
          "duration": 200,
          "offset": {
            "x": 46,
            "y": 197
          },
          "quad": {
            "x": 35,
            "y": 1,
            "w": 15,
            "h": 33
          }
        },
        {
          "duration": 200,
          "offset": {
            "x": 46,
            "y": 199
          },
          "quad": {
            "x": 1,
            "y": 36,
            "w": 15,
            "h": 31
          }
        },
        {
          "duration": 200,
          "offset": {
            "x": 46,
            "y": 196
          },
          "quad": {
            "x": 18,
            "y": 36,
            "w": 15,
            "h": 34
          }
        },
        {
          "duration": 200,
          "offset": {
            "x": 46,
            "y": 198
          },
          "quad": {
            "x": 35,
            "y": 36,
            "w": 15,
            "h": 32
          }
        },
        {
          "duration": 200,
          "offset": {
            "x": 46,
            "y": 199
          },
          "quad": {
            "x": 1,
            "y": 72,
            "w": 15,
            "h": 31
          }
        },
        {
          "duration": 200,
          "offset": {
            "x": 46,
            "y": 200
          },
          "quad": {
            "x": 18,
            "y": 72,
            "w": 15,
            "h": 30
          }
        }
      ]
    }
  }
}
