{
	"timelines": {
		"default": {
			"hitbox": {
				"aabb": {
					"x": 0,
					"y": 40,
					"w": 50,
					"h": 95
				}
			},
			"frames": [
				{
					"duration": 120,
					"offset": {
						"x": 0,
						"y": 40
					},
					"quad": {
						"x": 1,
						"y": 1,
						"w": 47,
						"h": 94
					}
				},
				{
					"duration": 120,
					"offset": {
						"x": 0,
						"y": 40
					},
					"quad": {
						"x": 1,
						"y": 97,
						"w": 47,
						"h": 94
					}
				},
				{
					"duration": 120,
					"offset": {
						"x": 0,
						"y": 40
					},
					"quad": {
						"x": 1,
						"y": 193,
						"w": 47,
						"h": 94
					}
				},
				{
					"duration": 120,
					"offset": {
						"x": 0,
						"y": 40
					},
					"quad": {
						"x": 1,
						"y": 1,
						"w": 47,
						"h": 94
					}
				},
				{
					"duration": 120,
					"offset": {
						"x": 0,
						"y": 40
					},
					"quad": {
						"x": 1,
						"y": 97,
						"w": 47,
						"h": 94
					}
				},
				{
					"duration": 120,
					"offset": {
						"x": 0,
						"y": 40
					},
					"quad": {
						"x": 1,
						"y": 193,
						"w": 47,
						"h": 94
					}
				},
				{
					"duration": 120,
					"offset": {
						"x": 0,
						"y": 40
					},
					"quad": {
						"x": 1,
						"y": 1,
						"w": 47,
						"h": 94
					}
				},
				{
					"duration": 120,
					"offset": {
						"x": 0,
						"y": 40
					},
					"quad": {
						"x": 1,
						"y": 97,
						"w": 47,
						"h": 94
					}
				}
			]
		},
		"lightning": {
			"next": "default",
			"hitbox": {
				"aabb": {
					"x": 0,
					"y": 40,
					"w": 50,
					"h": 95
				}
			},
			"frames": [
				{
					"duration": 120,
					"offset": {
						"x": 0,
						"y": 40
					},
					"quad": {
						"x": 1,
						"y": 289,
						"w": 47,
						"h": 94
					}
				},
				{
					"duration": 120,
					"offset": {
						"x": 0,
						"y": 40
					},
					"quad": {
						"x": 1,
						"y": 385,
						"w": 47,
						"h": 94
					}
				},
				{
					"duration": 120,
					"offset": {
						"x": 0,
						"y": 40
					},
					"quad": {
						"x": 1,
						"y": 481,
						"w": 47,
						"h": 94
					}
				}
			]
		}
	}
}
